alumni/__init__.py
alumni/admin.py
alumni/app_settings.py
alumni/apps.py
alumni/models.py
alumni/providers.py
alumni/signals.py
alumni/tasks.py
alumni/locale/de/LC_MESSAGES/django.mo
alumni/locale/de/LC_MESSAGES/django.po
alumni/locale/en/LC_MESSAGES/django.mo
alumni/locale/en/LC_MESSAGES/django.po
alumni/management/commands/__init__.py
alumni/management/commands/alumni_state.py
alumni/migrations/0001_initial.py
alumni/migrations/0002_auto_20211230_0147.py
alumni/migrations/0003_alter_alumnisetup_options_and_more.py
alumni/migrations/__init__.py
alumni/tests/__init__.py
aa_alumni-0.4.0.dist-info/licenses/LICENSE
aa_alumni-0.4.0.dist-info/WHEEL
aa_alumni-0.4.0.dist-info/METADATA
aa_alumni-0.4.0.dist-info/RECORD
