Metadata-Version: 2.4
Name: aa-alumni
Version: 0.4.0
Summary: Integration with Alliance Auths State System, creates and maintains an Alumni State for past members of an Alliance and/or Corporation
Keywords: allianceauth,eveonline
Author-email: Joel Falknau <joel.falknau@gmail.com>
Requires-Python: >=3.10
Classifier: Environment :: Web Environment
Classifier: Framework :: Celery
Classifier: Framework :: Django
Classifier: Framework :: Django :: 4.2
Classifier: Intended Audience :: Developers
Classifier: License :: OSI Approved :: MIT License
Classifier: Operating System :: OS Independent
Classifier: Programming Language :: Python
Classifier: Programming Language :: Python :: 3 :: Only
Classifier: Programming Language :: Python :: 3.10
Classifier: Programming Language :: Python :: 3.11
Classifier: Programming Language :: Python :: 3.12
Classifier: Programming Language :: Python :: 3.13
Classifier: Programming Language :: Python :: Implementation :: CPython
Classifier: Topic :: Internet :: WWW/HTTP
Classifier: Topic :: Internet :: WWW/HTTP :: Dynamic Content
License-File: LICENSE
Requires-Dist: allianceauth>=4.6.4,<6
Requires-Dist: django-solo>=2,<3
Project-URL: Homepage, https://gitlab.com/tactical-supremacy/aa-alumni
Project-URL: Source, https://gitlab.com/tactical-supremacy/aa-alumni
Project-URL: Tracker, https://gitlab.com/tactical-supremacy/aa-alumni/-/issues
